lib_off_campus_housing_parser/__init__.py
lib_off_campus_housing_parser/__main__.py
lib_off_campus_housing_parser/excel.py
lib_off_campus_housing_parser/google_maps.py
lib_off_campus_housing_parser/listing.py
lib_off_campus_housing_parser/logger.py
lib_off_campus_housing_parser/off_campus_parser.py
lib_off_campus_housing_parser-0.1.0.dist-info/LICENSE
lib_off_campus_housing_parser-0.1.0.dist-info/METADATA
lib_off_campus_housing_parser-0.1.0.dist-info/WHEEL
lib_off_campus_housing_parser-0.1.0.dist-info/entry_points.txt
lib_off_campus_housing_parser-0.1.0.dist-info/top_level.txt
lib_off_campus_housing_parser-0.1.0.dist-info/RECORD
